{
  "data": {
    "contents": {
      "0": {
        "imgSrc": "https://placehold.jp/400x160.png",
        "alt": "",
        "width": "",
        "spWidth": "",
        "userEditWidth": 0,
        "spUserEditWidth": 0,
        "editWidth": false,
        "href": "",
        "target": ""
      },
      "1": {
        "text": "あいうえおかきくけこさしすせそたちつてとなにぬねのはひふへほまみむめもやゃゆゅよらりるれろわ・を・んアイウエオカキクケコサシスセソタチツテトナニヌネノハヒフヘホマミムメモヤャユュヨララリルレロワ・ヲ・ン"
      }
    },
    "imageDirection": "R",
    "imageFloat": true
  },
  "partsVariations": "",
  "templateDir": "sideBoxMediaBox"
}